somacore/__init__.py
somacore/_mixin.py
somacore/_version.py
somacore/base.py
somacore/collection.py
somacore/coordinates.py
somacore/data.py
somacore/experiment.py
somacore/measurement.py
somacore/options.py
somacore/py.typed
somacore/scene.py
somacore/spatial.py
somacore/types.py
somacore/query/__init__.py
somacore/query/axis.py
somacore/query/query.py
somacore/query/types.py
somacore-1.0.29.dist-info/licenses/LICENSE
somacore-1.0.29.dist-info/METADATA
somacore-1.0.29.dist-info/WHEEL
somacore-1.0.29.dist-info/top_level.txt
somacore-1.0.29.dist-info/RECORD
