Metadata-Version: 2.4
Name: somacore
Version: 1.0.29
Summary: Python-language API specification and base utilities for implementation of the SOMA system.
Project-URL: repository, https://github.com/single-cell-data/SOMA.git
Classifier: License :: OSI Approved :: MIT License
Requires-Python: >=3.9
License-File: LICENSE
Requires-Dist: anndata
Requires-Dist: attrs>=22.1
Requires-Dist: numpy>=1.21
Requires-Dist: pandas
Requires-Dist: pyarrow
Requires-Dist: pyarrow-hotfix
Requires-Dist: scipy
Requires-Dist: shapely
Requires-Dist: typing-extensions>=4.1
Provides-Extra: dev
Requires-Dist: black; extra == "dev"
Requires-Dist: isort; extra == "dev"
Requires-Dist: mypy~=1.0; extra == "dev"
Requires-Dist: ruff; extra == "dev"
Requires-Dist: pandas-stubs; extra == "dev"
Dynamic: license-file
